edgeimpulse/__init__.py
edgeimpulse/data/__init__.py
edgeimpulse/data/_functions/delete.py
edgeimpulse/data/_functions/download.py
edgeimpulse/data/_functions/upload.py
edgeimpulse/data/_functions/upload_files.py
edgeimpulse/data/_functions/upload_numpy.py
edgeimpulse/data/_functions/upload_pandas.py
edgeimpulse/data/_functions/util.py
edgeimpulse/data/sample_type.py
edgeimpulse/datasets/__init__.py
edgeimpulse/datasets/_functions/_datasets.py
edgeimpulse/exceptions.py
edgeimpulse/experimental/__init__.py
edgeimpulse/experimental/api.py
edgeimpulse/experimental/data/__init__.py
edgeimpulse/experimental/impulse/__init__.py
edgeimpulse/experimental/tuner/__init__.py
edgeimpulse/experimental/util/__init__.py
edgeimpulse/impulse/__init__.py
edgeimpulse/impulse/_functions/build.py
edgeimpulse/model/__init__.py
edgeimpulse/model/_functions/__init__.py
edgeimpulse/model/_functions/deploy.py
edgeimpulse/model/_functions/profile.py
edgeimpulse/model/input_type.py
edgeimpulse/model/model_info.py
edgeimpulse/model/output_type.py
edgeimpulse/tuner/__init__.py
edgeimpulse/tuner/_functions/tuner.py
edgeimpulse/util.py
edgeimpulse-1.0.17.dist-info/LICENSE
edgeimpulse-1.0.17.dist-info/METADATA
edgeimpulse-1.0.17.dist-info/WHEEL
edgeimpulse-1.0.17.dist-info/RECORD
