Metadata-Version: 2.1
Name: edgeimpulse
Version: 1.0.17
Summary: Python SDK for Edge Impulse.
Home-page: https://edgeimpulse.com
License: Apache-2.0
Author: EdgeImpulse Inc.
Author-email: hello@edgeimpulse.com
Requires-Python: >=3.8,<4.0
Classifier: License :: OSI Approved :: Apache Software License
Classifier: Programming Language :: Python :: 3
Classifier: Programming Language :: Python :: 3.8
Classifier: Programming Language :: Python :: 3.9
Classifier: Programming Language :: Python :: 3.10
Classifier: Programming Language :: Python :: 3.11
Classifier: Topic :: Scientific/Engineering :: Artificial Intelligence
Classifier: Topic :: Software Development :: Embedded Systems
Requires-Dist: edgeimpulse-api (>=1.61.21,<2.0.0)
Requires-Dist: python-socketio[client] (>=5.8.0,<6.0.0)
Requires-Dist: requests (>=2.23.0,<3.0.0)
Project-URL: Documentation, https://docs.edgeimpulse.com/docs/edge-impulse-python-sdk/overview
Project-URL: Repository, https://github.com/edgeimpulse/python-sdk
